{
 "fetchedAt": "2026-07-23T17:49:09.675Z",
 "byBout": {
  "401874311": {
   "pA": 0.736,
   "books": 8,
   "commence": "2026-07-25T09:00:00Z",
   "priceA": 1.3,
   "priceB": 3.63,
   "totals": [
    {
     "point": 2.5,
     "over": 1.67,
     "under": 2.2,
     "books": 5
    }
   ]
  },
  "401874312": {
   "pA": 0.375,
   "books": 8,
   "commence": "2026-07-25T09:00:00Z",
   "priceA": 2.56,
   "priceB": 1.53,
   "totals": [
    {
     "point": 1.5,
     "over": 1.62,
     "under": 2.32,
     "books": 4
    },
    {
     "point": 2.5,
     "over": 2.1,
     "under": 1.69,
     "books": 1
    }
   ]
  },
  "401874314": {
   "pA": 0.137,
   "books": 7,
   "commence": "2026-07-25T13:45:00Z",
   "priceA": 7.03,
   "priceB": 1.11,
   "totals": [
    {
     "point": 1.5,
     "over": 2.9,
     "under": 1.42,
     "books": 4
    },
    {
     "point": 0.5,
     "over": 1.4,
     "under": 2.85,
     "books": 1
    }
   ]
  },
  "401874315": {
   "pA": 0.503,
   "books": 6,
   "commence": "2026-07-25T09:00:00Z",
   "priceA": 1.89,
   "priceB": 1.92,
   "totals": [
    {
     "point": 2.5,
     "over": 1.55,
     "under": 2.44,
     "books": 5
    }
   ]
  },
  "401874316": {
   "pA": 0.131,
   "books": 8,
   "commence": "2026-07-25T09:00:00Z",
   "priceA": 7.36,
   "priceB": 1.1,
   "totals": [
    {
     "point": 1.5,
     "over": 3.18,
     "under": 1.35,
     "books": 5
    }
   ]
  },
  "401874317": {
   "pA": 0.353,
   "books": 8,
   "commence": "2026-07-25T09:00:00Z",
   "priceA": 2.71,
   "priceB": 1.48,
   "totals": [
    {
     "point": 2.5,
     "over": 2.08,
     "under": 1.74,
     "books": 5
    }
   ]
  },
  "401878072": {
   "pA": 0.656,
   "books": 5,
   "commence": "2026-08-16T03:00:00Z",
   "priceA": 1.45,
   "priceB": 2.77,
   "totals": []
  },
  "401886732": {
   "pA": 0.719,
   "books": 8,
   "commence": "2026-07-25T09:00:00Z",
   "priceA": 1.33,
   "priceB": 3.41,
   "totals": [
    {
     "point": 1.5,
     "over": 1.44,
     "under": 2.8,
     "books": 4
    },
    {
     "point": 2.5,
     "over": 1.74,
     "under": 2.05,
     "books": 1
    }
   ]
  },
  "401886737": {
   "pA": 0.334,
   "books": 8,
   "commence": "2026-07-25T09:00:00Z",
   "priceA": 2.87,
   "priceB": 1.44,
   "totals": [
    {
     "point": 2.5,
     "over": 1.46,
     "under": 2.71,
     "books": 5
    }
   ]
  },
  "401887532": {
   "pA": 0.222,
   "books": 4,
   "commence": "2026-08-29T20:00:00Z",
   "priceA": 4.3,
   "priceB": 1.23,
   "totals": []
  },
  "401890156": {
   "pA": 0.688,
   "books": 8,
   "commence": "2026-07-25T16:15:00Z",
   "priceA": 1.39,
   "priceB": 3.07,
   "totals": [
    {
     "point": 2.5,
     "over": 1.46,
     "under": 2.74,
     "books": 4
    }
   ]
  },
  "401891531": {
   "pA": 0.209,
   "books": 8,
   "commence": "2026-07-25T09:00:00Z",
   "priceA": 4.58,
   "priceB": 1.21,
   "totals": [
    {
     "point": 1.5,
     "over": 2.05,
     "under": 1.76,
     "books": 5
    }
   ]
  },
  "401892276": {
   "pA": 0.813,
   "books": 8,
   "commence": "2026-07-25T09:00:00Z",
   "priceA": 1.17,
   "priceB": 5.11,
   "totals": [
    {
     "point": 2.5,
     "over": 2.18,
     "under": 1.69,
     "books": 5
    }
   ]
  },
  "401898030": {
   "pA": 0.195,
   "books": 8,
   "commence": "2026-07-25T13:10:00Z",
   "priceA": 4.89,
   "priceB": 1.19,
   "totals": [
    {
     "point": 2.5,
     "over": 2.47,
     "under": 1.56,
     "books": 4
    },
    {
     "point": 1.5,
     "over": 1.77,
     "under": 2,
     "books": 1
    }
   ]
  },
  "401898040": {
   "pA": 0.605,
   "books": 8,
   "commence": "2026-07-25T15:15:00Z",
   "priceA": 1.58,
   "priceB": 2.43,
   "totals": [
    {
     "point": 1.5,
     "over": 1.55,
     "under": 2.47,
     "books": 4
    },
    {
     "point": 2.5,
     "over": 1.95,
     "under": 1.8,
     "books": 1
    }
   ]
  }
 }
}